Metadata-Version: 2.1
Name: snspoliciestocsv
Version: 1.12
Summary: A simple script to extract policies from a Stormshield Network Security device configuration file to CSV
Home-page: https://github.com/maaaaz/snspoliciestocsv
Author: Thomas D.
Author-email: tdebize@mail.com
License: LGPL
Keywords: stormshield network security configuration csv
Platform: UNKNOWN
Classifier: Topic :: Security
Classifier: Development Status :: 5 - Production/Stable
Classifier: Intended Audience :: Information Technology
Classifier: License :: OSI Approved :: GNU Library or Lesser General Public License (LGPL)
Requires-Python: >=3
